u_stats/__init__.py
u_stats/_utils/__init__.py
u_stats/_utils/_alphabet.py
u_stats/_utils/_backend.py
u_stats/_utils/_convert.py
u_stats/_utils/_typing.py
u_stats/statistics/__init__.py
u_stats/statistics/classical.py
u_stats/statistics/mode_lib.py
u_stats/statistics/u2v.py
u_stats/statistics/ustats.py
u_stats/statistics/vstats.py
u_stats-0.7.6.dist-info/licenses/LICENSE
u_stats-0.7.6.dist-info/METADATA
u_stats-0.7.6.dist-info/WHEEL
u_stats-0.7.6.dist-info/top_level.txt
u_stats-0.7.6.dist-info/RECORD
