Metadata-Version: 2.4
Name: u-stats
Version: 0.7.6
Summary: A Python package for U-Statistics calculation
Author-email: Ruiqi Zhang <zrq1706@outlook.com>
License: MIT
Project-URL: Homepage, https://github.com/Amedar-Asterisk/U-Statistics-python
Project-URL: Repository, https://github.com/Amedar-Asterisk/U-Statistics-python
Project-URL: Bug Tracker, https://github.com/Amedar-Asterisk/U-Statistics-python/issues
Keywords: statistics,u-statistics,v-statistics,tensor,numpy
Classifier: Development Status :: 4 - Beta
Classifier: Intended Audience :: Science/Research
Classifier: License :: OSI Approved :: MIT License
Classifier: Operating System :: OS Independent
Classifier: Programming Language :: Python :: 3
Classifier: Programming Language :: Python :: 3.11
Classifier: Programming Language :: Python :: 3.12
Classifier: Topic :: Scientific/Engineering :: Mathematics
Classifier: Topic :: Software Development :: Libraries :: Python Modules
Requires-Python: >=3.11
License-File: LICENSE
Requires-Dist: numpy>=1.20.0
Requires-Dist: opt_einsum>=3.3.0
Provides-Extra: test
Requires-Dist: pytest>=7.0; extra == "test"
Requires-Dist: pytest-cov; extra == "test"
Provides-Extra: dev
Requires-Dist: pytest>=7.0; extra == "dev"
Requires-Dist: pytest-cov; extra == "dev"
Requires-Dist: mypy; extra == "dev"
Requires-Dist: black; extra == "dev"
Requires-Dist: flake8; extra == "dev"
Requires-Dist: isort; extra == "dev"
Dynamic: license-file
